aipkgs_notifications/__init__.py
aipkgs_notifications/enums.py
aipkgs_notifications/ns.py
aipkgs_notifications/payload.py
aipkgs_notifications/response.py
aipkgs_notifications/singleton.py
aipkgs_notifications/utils.py
aipkgs_notifications-1.0.2.dist-info/LICENSE.md
aipkgs_notifications-1.0.2.dist-info/METADATA
aipkgs_notifications-1.0.2.dist-info/WHEEL
aipkgs_notifications-1.0.2.dist-info/RECORD
