Metadata-Version: 2.1
Name: aipkgs-notifications
Version: 1.0.2
Summary: A simple package to send notifications to your devices using Firebase Cloud Messaging.
Home-page: https://github.com/AlexyIbrahim/Notifications
License: MIT
Keywords: ai
Author: Alexy
Author-email: alexy.ib@outlook.com
Requires-Python: >=3.11.4,<4.0.0
Classifier: License :: OSI Approved :: MIT License
Classifier: Programming Language :: Python :: 3
Classifier: Programming Language :: Python :: 3.12
Requires-Dist: cryptography (>=41.0.5,<42.0.0)
Requires-Dist: firebase-admin (>=6.3.0,<7.0.0)
Requires-Dist: httpx[http2] (>=0.25.0,<0.26.0)
Requires-Dist: pyjwt (>=2.8.0,<3.0.0)
Project-URL: Repository, https://github.com/AlexyIbrahim/Notifications
